eyja/__init__.py
eyja/constants/__init__.py
eyja/constants/types/__init__.py
eyja/constants/types/config_types.py
eyja/constants/types/plugin_types.py
eyja/errors/__init__.py
eyja/errors/base_error.py
eyja/errors/hub_errors.py
eyja/errors/model_errors.py
eyja/hubs/__init__.py
eyja/hubs/base_hub/__init__.py
eyja/hubs/base_hub/base_hub.py
eyja/hubs/config_hub/__init__.py
eyja/hubs/config_hub/config_hub.py
eyja/hubs/data_hub/__init__.py
eyja/hubs/data_hub/data_hub.py
eyja/hubs/plugin_hub/__init__.py
eyja/hubs/plugin_hub/plugin_hub.py
eyja/interfaces/__init__.py
eyja/interfaces/db/__init__.py
eyja/interfaces/db/base_data_model.py
eyja/interfaces/db/base_storage_client.py
eyja/interfaces/db/base_storage_model.py
eyja/interfaces/db/data_filter.py
eyja/interfaces/operators/__init__.py
eyja/interfaces/operators/base_operator.py
eyja/interfaces/operators/model_operator.py
eyja/interfaces/plugins/__init__.py
eyja/interfaces/plugins/base_plugin.py
eyja/logging/__init__.py
eyja/logging/console_logger.py
eyja/main/__init__.py
eyja/main/eyja.py
eyja/services/__init__.py
eyja/services/service.py
eyja/utils/__init__.py
eyja/utils/dt.py
eyja/utils/encoders.py
eyja/utils/imports.py
eyja/utils/strings.py
tests/__init__.py
tests/test_hubs/__init__.py
tests/test_hubs/test_plugin_hub.py
tests/test_main/__init__.py
tests/test_main/test_eyja.py
tests/test_models/__init__.py
tests/test_models/test_base_model.py
tests/test_utils/__init__.py
tests/test_utils/test_imports.py
eyja_internal-0.5.3.dist-info/METADATA
eyja_internal-0.5.3.dist-info/WHEEL
eyja_internal-0.5.3.dist-info/top_level.txt
eyja_internal-0.5.3.dist-info/zip-safe
eyja_internal-0.5.3.dist-info/RECORD
