Metadata-Version: 2.1
Name: eyja-internal
Version: 0.5.3
Summary: Smart async framework
Home-page: https://gitlab.com/public.eyja.dev/eyja-internal
Maintainer: Anton Berdnikov
Maintainer-email: agratoth@yandex.ru
License: UNKNOWN
Platform: UNKNOWN
Classifier: License :: OSI Approved :: MIT License
Classifier: Operating System :: OS Independent
Classifier: Programming Language :: Python
Classifier: Programming Language :: Python :: 3.8
Classifier: Programming Language :: Python :: 3.9
Requires-Python: >=3.8
Requires-Dist: aiofiles (>=0.8.0)
Requires-Dist: pydantic (>=1.8.2)
Requires-Dist: pytz (>=2021.3)
Requires-Dist: PyYAML (>=6.0)
Requires-Dist: jinja2 (>=3.0.3)
Requires-Dist: uvloop (>=0.16.0)
